test_plus/__init__.py
test_plus/admin.py
test_plus/apps.py
test_plus/models.py
test_plus/tests.py
test_plus/views.py
test_plus/management/__init__.py
test_plus/management/commands/__init__.py
test_plus/management/commands/test_plus.py
test_plus/migrations/__init__.py
test_plus-0.1.10.dist-info/LICENSE
test_plus-0.1.10.dist-info/METADATA
test_plus-0.1.10.dist-info/WHEEL
test_plus-0.1.10.dist-info/top_level.txt
test_plus-0.1.10.dist-info/RECORD
