Metadata-Version: 2.1
Name: test-plus
Version: 0.1.10
Summary: Test analysis tool for Django
Home-page: https://github.com/tolgahanuzun/test_plus
Author: Tolgahan Üzün
Author-email: mail@tolgahanuzun.com
License: UNKNOWN
Download-URL: https://github.com/tolgahanuzun/test_plus/tarball/0.1.10
Keywords: django,test,time
Platform: UNKNOWN
